ex4ml/__init__.py
ex4ml/content/__init__.py
ex4ml/content/report.py
ex4ml/content/visualize.py
ex4ml/deep/__init__.py
ex4ml/deep/nn.py
ex4ml/experiments/__init__.py
ex4ml/experiments/experiments_helpers.py
ex4ml/experiments/supervised.py
ex4ml/experiments/unsupervised.py
ex4ml/explainers/__init__.py
ex4ml/statistical/__init__.py
ex4ml/tools/__init__.py
ex4ml/tools/datatools.py
ex4ml/tools/filetools.py
ex4ml-1.0a0.dist-info/LICENSE.txt
ex4ml-1.0a0.dist-info/WHEEL
ex4ml-1.0a0.dist-info/METADATA
ex4ml-1.0a0.dist-info/RECORD
